{
  "": "",
  "Cсылка на аватар": "",
  "Cсылку на аватар": "",
  "Ваш ": "",
  "Ваш возраст": "",
  "Ваша фамилия": "",
  "Ваше имя": "",
  "Ваше фамилия": "",
  "Введите имя пользователя": "",
  "Введите ссылку на аватар": "",
  "Возраст": "",
  "Город": "",
  "Данные не указаны": "",
  "Имя": "",
  "Имя и фамилия обязательны": "",
  "Имя пользователя": "",
  "Некоректный ": "",
  "Некорректный ": "",
  "Некорректный возраст": "",
  "Некорректный регион": "",
  "Ошибка": "",
  "Попробуйте обновить страницу": "",
  "Попробуйте перезагру": "",
  "Попробуйте перезагрузить страницу": "",
  "Произошла ошибка": "",
  "Произошла ошибка при загрузке профиля": "",
  "Профиль": "",
  "Профиль не найден": "",
  "Редактировать": "",
  "Серверная ошибка при сохранении": "",
  "Ссылка на аватар": "",
  "Укажите валюту": "",
  "Фамилия": "",
  "амилия": "",
  "мя пользователя": ""
}
